transport_frames/__init__.py
transport_frames/criteria.py
transport_frames/frame.py
transport_frames/graph.py
transport_frames/indicators.py
transport_frames/road_adder.py
transport_frames/transport_provision.py
transport_frames/utils/__init__.py
transport_frames/utils/helper_funcs.py
transport_frames-2.0.5.dist-info/LICENSE
transport_frames-2.0.5.dist-info/METADATA
transport_frames-2.0.5.dist-info/WHEEL
transport_frames-2.0.5.dist-info/top_level.txt
transport_frames-2.0.5.dist-info/RECORD
